cognite/tracing/__init__.py
cognite/tracing/config.py
cognite/tracing/initialize.py
cognite/tracing/py.typed
cognite/tracing/span.py
cognite/tracing/traced.py
cognite_tracing-0.2.2.dist-info/LICENSE
cognite_tracing-0.2.2.dist-info/WHEEL
cognite_tracing-0.2.2.dist-info/METADATA
cognite_tracing-0.2.2.dist-info/RECORD
