Metadata-Version: 2.1
Name: cognite-tracing
Version: 0.2.2
Summary: Library for tracing using Lightstep
Author: Vegard Stikbakke
Author-email: vegard.stikbakke@gmail.com
Requires-Python: >=3.7,<4.0
Classifier: Programming Language :: Python :: 3
Classifier: Programming Language :: Python :: 3.10
Classifier: Programming Language :: Python :: 3.7
Classifier: Programming Language :: Python :: 3.8
Classifier: Programming Language :: Python :: 3.9
Requires-Dist: elastic-apm[opentracing] (>=6.6.1,<7.0.0)
Requires-Dist: lightstep (>=4.4.7,<5.0.0)
Requires-Dist: opentracing (>=2.3.0,<3.0.0)
